realtimex_agent_a2a_agent/__init__.py
realtimex_agent_a2a_agent/agent.py
realtimex_agent_a2a_agent/callbacks/tool_execution.py
realtimex_agent_a2a_agent/cli.py
realtimex_agent_a2a_agent/tools.py
realtimex_agent_a2a_agent-0.5.0.dist-info/WHEEL
realtimex_agent_a2a_agent-0.5.0.dist-info/entry_points.txt
realtimex_agent_a2a_agent-0.5.0.dist-info/METADATA
realtimex_agent_a2a_agent-0.5.0.dist-info/RECORD
