Metadata-Version: 2.3
Name: realtimex-agent-a2a-agent
Version: 0.5.0
Summary: Add your description here
Author: rta_phuongnguyen
Author-email: rta_phuongnguyen <phuongnguyen@rtanalytics.vn>
Requires-Dist: realtimex-any-agent
Requires-Dist: ollama
Requires-Dist: google-genai
Requires-Dist: realtimex-any-agent[a2a]
Requires-Dist: realtimex-any-agent[langchain]
Requires-Dist: realtimex-any-agent[deepagents]
Requires-Dist: nest-asyncio
Requires-Dist: openai
Requires-Dist: aci-mcp==1.0.0b13
Requires-Dist: mem0ai==0.1.116
Requires-Dist: redis
Requires-Python: >=3.11
